{
    "mappings": [
        {
            "id": "admin",
            "roles": [
                "admin",
                "author",
                "user"
            ]
        },
        {
            "id": "user",
            "roles": [
                "user"
            ]
        },
        {
            "id": "eventprocessing-admin",
            "roles": [
                "admin",
                "author",
                "user"
            ]
        },
        {
            "id": "eventprocessing-viewer",
            "roles": [
                "user"
            ]
        }
    ]
}